kaltura_mcp/__init__.py
kaltura_mcp/kaltura_client.py
kaltura_mcp/prompts.py
kaltura_mcp/proxy_client.py
kaltura_mcp/remote_server.py
kaltura_mcp/resources.py
kaltura_mcp/server.py
kaltura_mcp/tools/__init__.py
kaltura_mcp/tools/analytics.py
kaltura_mcp/tools/analytics_core.py
kaltura_mcp/tools/assets.py
kaltura_mcp/tools/media.py
kaltura_mcp/tools/search.py
kaltura_mcp/tools/utils.py
mseep_kaltura_mcp-0.2.1.dist-info/licenses/LICENSE
mseep_kaltura_mcp-0.2.1.dist-info/METADATA
mseep_kaltura_mcp-0.2.1.dist-info/WHEEL
mseep_kaltura_mcp-0.2.1.dist-info/entry_points.txt
mseep_kaltura_mcp-0.2.1.dist-info/top_level.txt
mseep_kaltura_mcp-0.2.1.dist-info/RECORD
